Workbook

Sheet Raw Data
A1: Bank | B1: Year | C1: Net Income | D1: Total Assets | E1: Total Equity | F1: Loans | G1: Deposits | H1: Net Interest Income | I1: CET1 | J1: ROE | K1: ROA | L1: Net Yield | M1: Cost-to-Income | N1: Loan-to-Deposit | O1: LCR | P1: FX Rate
A2: JPMorgan Chase | B2: 2025 | C2: 57000 | D2: 4424900 | E2: 362438 | F2: 1493429 | G2: 2559320 | H2: 96443 | I2: 0.146 | J2: =C2/AVERAGE(E2,E3) -> 0.16120001 | K2: =C2/AVERAGE(D2,D3) -> 0.0135268 | L2: 0.022 | M2: 0.49 | N2: =F2/G2 -> 0.5835257 | O2: 1.11
A3: JPMorgan Chase | B3: 2024 | C3: 58471 | D3: 4002814 | E3: 344758 | F3: 1347988 | G3: 2406032 | H3: 92583 | I3: 0.157 | J3: =C3/AVERAGE(E3,E4) -> 0.17385629 | K3: =C3/AVERAGE(D3,D4) -> 0.014843733 | L3: 0.026 | M3: 0.5 | N3: =F3/G3 -> 0.56025356 | O3: 1.13
A4: JPMorgan Chase | B4: 2023 | C4: 49552 | D4: 3875393 | E4: 327878 | F4: 1323706 | G4: 2400688 | H4: 88267 | I4: 0.15 | J4: =C4/AVERAGE(E4,E5) -> 0.15979104 | K4: =C4/AVERAGE(D4,D5) -> 0.013141787 | L4: 0.028 | M4: 0.53 | N4: =F4/G4 -> 0.5513861 | O4: 1.13
A5: JPMorgan Chase | B5: 2022 | C5: 37676 | D5: 3665743 | E5: 292332 | F5: 1032282 | G5: 2340005 | H5: 66710 | I5: 0.132 | J5: =C5/AVERAGE(E5,E6) -> 0.1284877 | K5: =C5/AVERAGE(D5,D6) -> 0.010169908 | L5: 0.022 | M5: 0.59 | N5: =F5/G5 -> 0.44114521 | O5: 1.12
A6: JPMorgan Chase | B6: 2021 | C6: 48334 | D6: 3743567 | E6: 294121 | F6: 1077857 | G6: 2462292 | H6: 52311 | I6: 0.131 | J6: =C6/AVERAGE(E6,279354) -> 0.16856533 | K6: =C6/AVERAGE(D6,3386071) -> 0.013558613 | L6: 0.019 | M6: 0.59 | N6: =F6/G6 -> 0.4377454 | O6: 1.11
A7: Bank of America | B7: 2025 | C7: 30509 | D7: 3410394 | E7: 303243 | F7: 1185700 | G7: 2018729 | H7: 60096 | I7: 0.114 | J7: =C7/AVERAGE(E7,E8) -> 0.10217245 | K7: =C7/AVERAGE(D7,D8) -> 0.0091458045 | L7: 0.0201 | M7: 0.6275 | N7: =F7/G7 -> 0.58734976 | O7: 1.12
A8: Bank of America | B8: 2024 | C8: 26973 | D8: 3261299 | E8: 293963 | F8: 1095835 | G8: 1965467 | H8: 56060 | I8: 0.119 | J8: =C8/AVERAGE(E8,E9) -> 0.092119486 | K8: =C8/AVERAGE(D8,D9) -> 0.0083748224 | L8: 0.0195 | M8: 0.6304 | N8: =F8/G8 -> 0.55754434 | O8: 1.13
A9: Bank of America | B9: 2023 | C9: 26515 | D9: 3180151 | E9: 291646 | F9: 1053732 | G9: 1923827 | H9: 56931 | I9: 0.118 | J9: =C9/AVERAGE(E9,E10) -> 0.093884495 | K9: =C9/AVERAGE(D9,D10) -> 0.0085108678 | L9: 0.0208 | M9: 0.6641 | N9: =F9/G9 -> 0.547727 | O9: 1.15
A10: Bank of America | B10: 2022 | C10: 27528 | D10: 3050706 | E10: 273197 | F10: 1045747 | G10: 1930341 | H10: 51462 | I10: 0.112 | J10: =C10/AVERAGE(E10,E11) -> 0.10134318 | K10: =C10/AVERAGE(D10,D11) -> 0.0088505164 | L10: 0.0196 | M10: 0.6441 | N10: =F10/G10 -> 0.54174211 | O10: 1.2
A11: Bank of America | B11: 2021 | C11: 31978 | D11: 3169948 | E11: 270066 | F11: 979124 | G11: 2064446 | H11: 42934 | I11: 0.106 | J11: =C11/AVERAGE(E11,272924) -> 0.11778486 | K11: 0.0105 | L11: 0.0166 | M11: 0.6671 | N11: =F11/G11 -> 0.4742793 | O11: 1.15
A12: Wells Fargo | B12: 2025 | C12: 21338 | D12: 2148631 | E12: 183038 | F12: 986167 | G12: 1426207 | H12: 47484 | I12: 0.106 | J12: =C12/AVERAGE(E12,E13) -> 0.11720827 | K12: =C12/AVERAGE(D12,D13) -> 0.010463712 | L12: 0.0267 | M12: 0.66 | N12: =F12/G12 -> 0.69146134 | O12: 1.19
A13: Wells Fargo | B13: 2024 | C13: 19772 | D13: 1929845 | E13: 181066 | F13: 912745 | G13: 1371804 | H13: 47676 | I13: 0.1107 | J13: =C13/AVERAGE(E13,E14) -> 0.1073081 | K13: =C13/AVERAGE(D13,D14) -> 0.010238424 | L13: 0.0273 | M13: 0.66 | N13: =F13/G13 -> 0.66536109 | O13: 1.25
A14: Wells Fargo | B14: 2023 | C14: 19142 | D14: 1932468 | E14: 187443 | F14: 936682 | G14: 1358173 | H14: 52375 | I14: 0.1143 | J14: =C14/AVERAGE(E14,E15) -> 0.10390301 | K14: =C14/AVERAGE(D14,D15) -> 0.010039114 | L14: 0.0306 | M14: 0.67 | N14: =F14/G14 -> 0.68966325 | O14: 1.25
A15: Wells Fargo | B15: 2022 | C15: 13182 | D15: 1881016 | E15: 181016 | F15: 955871 | G15: 1383985 | H15: 44950 | I15: 0.106 | J15: =C15/AVERAGE(E15,E16) -> 0.071037869 | K15: =C15/AVERAGE(D15,D16) -> 0.0068851976 | L15: 0.0246 | M15: 0.77 | N15: =F15/G15 -> 0.69066572 | O15: 1.22
A16: Wells Fargo | B16: 2021 | C16: 21548 | D16: 1948068 | E16: 190110 | F16: 895394 | G16: 1482479 | H16: 35779 | I16: 0.1135 | J16: =C16/AVERAGE(E16,185712) -> 0.11467131 | K16: =C16/AVERAGE(D16,1952911) -> 0.011047483 | L16: 0.0203 | M16: 0.69 | N16: =F16/G16 -> 0.60398427 | O16: 1.18
A17: Citigroup | B17: 2025 | C17: 14306 | D17: 2657202 | E17: 212291 | F17: 752230 | G17: 1403573 | H17: 59792 | I17: 0.1318 | J17: =C17/AVERAGE(E17,E18) -> 0.067979919 | K17: =C17/AVERAGE(D17,D18) -> 0.0057108105 | L17: 0.0247 | M17: 0.647 | N17: =F17/G17 -> 0.53593935 | O17: 1.15
A18: Citigroup | B18: 2024 | C18: 12682 | D18: 2352945 | E18: 208598 | F18: 694488 | G18: 1284458 | H18: 54095 | I18: 0.1363 | J18: =C18/AVERAGE(E18,E19) -> 0.061258154 | K18: =C18/AVERAGE(D18,D19) -> 0.005323227 | L18: 0.024 | M18: 0.664 | N18: =F18/G18 -> 0.54068564 | O18: 1.16
A19: Citigroup | B19: 2023 | C19: 9228 | D19: 2411834 | E19: 205453 | F19: 689362 | G19: 1308681 | H19: 54900 | I19: 0.1337 | J19: =C19/AVERAGE(E19,E20) -> 0.04538636 | K19: =C19/AVERAGE(D19,D20) -> 0.0038222971 | L19: 0.0246 | M19: 0.717 | N19: =F19/G19 -> 0.52676091 | O19: 1.16
A20: Citigroup | B20: 2022 | C20: 14845 | D20: 2416676 | E20: 201189 | F20: 657221 | G20: 1365954 | H20: 48688 | I20: 0.1303 | J20: =C20/AVERAGE(E20,E21) -> 0.073643036 | K20: =C20/AVERAGE(D20,D21) -> 0.006306168 | L20: 0.0225 | M20: 0.679 | N20: =F20/G20 -> 0.48114431 | O20: 1.18
A21: Citigroup | B21: 2021 | C21: 21952 | D21: 2291413 | E21: 201972 | F21: 667767 | G21: 1317230 | H21: 42494 | I21: 0.1225 | J21: =C21/AVERAGE(E21,199442) -> 0.10937337 | K21: =C21/AVERAGE(D21,2260090) -> 0.0096460444 | L21: 0.0199 | M21: 0.669 | N21: =F21/G21 -> 0.50694791 | O21: 1.15
A22: Goldman Sachs | B22: 2025 | C22: 17176 | D22: 1809320 | E22: 124972 | F22: 239882 | G22: 501422 | H22: 13559 | I22: 0.15 | J22: =C22/AVERAGE(E22,E23) -> 0.13909494 | K22: =C22/AVERAGE(D22,D23) -> 0.009856276 | L22: - | M22: 0.644 | N22: =F22/G22 -> 0.47840342 | O22: 1.22
A23: Goldman Sachs | B23: 2024 | C23: 14276 | D23: 1675972 | E23: 121996 | F23: 200866 | G23: 433013 | H23: 8056 | I23: 0.15 | J23: =C23/AVERAGE(E23,E24) -> 0.11951394 | K23: =C23/AVERAGE(D23,D24) -> 0.0086063096 | L23: 0.0273 | M23: 0.631 | N23: =F23/G23 -> 0.46387984 | O23: 1.29
A24: Goldman Sachs | B24: 2023 | C24: 8516 | D24: 1641594 | E24: 116905 | F24: 183358 | G24: 428417 | H24: 6351 | I24: 0.144 | J24: =C24/AVERAGE(E24,E25) -> 0.072757098 | K24: =C24/AVERAGE(D24,D25) -> 0.005523785 | L24: 0.0225 | M24: 0.746 | N24: =F24/G24 -> 0.42798955 | O24: 1.28
A25: Goldman Sachs | B25: 2022 | C25: 11261 | D25: 1441799 | E25: 117189 | F25: 179286 | G25: 386665 | H25: 7678 | I25: 0.15 | J25: =C25/AVERAGE(E25,E26) -> 0.099165621 | K25: =C25/AVERAGE(D25,D26) -> 0.0077507402 | L25: 0.0246 | M25: 0.658 | N25: =F25/G25 -> 0.46367269 | O25: 1.26
A26: Goldman Sachs | B26: 2021 | C26: 21635 | D26: 1463988 | E26: 109926 | F26: 158562 | G26: 364227 | H26: 6470 | I26: 0.142 | J26: =C26/AVERAGE(E26,95932) -> 0.21019343 | K26: =C26/AVERAGE(D26,1163028) -> 0.01647116 | L26: 0.0199 | M26: 0.538 | N26: =F26/G26 -> 0.4353384 | O26: 1.23
A27: Morgan Stanley | B27: 2025 | C27: 17025 | D27: 1420270 | E27: 112652 | F27: 289038 | G27: 415523 | H27: 10046 | I27: 0.15 | J27: =C27/AVERAGE(E27,E28) -> 0.15613536 | K27: =C27/AVERAGE(D27,D28) -> 0.012920529 | L27: 0.025 | M27: 0.68 | N27: =F27/G27 -> 0.69560048 | O27: 1.34
A28: Morgan Stanley | B28: 2024 | C28: 13529 | D28: 1215071 | E28: 105428 | F28: 246814 | G28: 376007 | H28: 8611 | I28: 0.159 | J28: =C28/AVERAGE(E28,E29) -> 0.13172679 | K28: =C28/AVERAGE(D28,D29) -> 0.011233147 | L28: 0.026 | M28: 0.71 | N28: =F28/G28 -> 0.65640799 | O28: 1.3
A29: Morgan Stanley | B29: 2023 | C29: 9230 | D29: 1193693 | E29: 99982 | F29: - | G29: - | H29: 8230 | I29: 0.155 | J29: =C29/AVERAGE(E29,E30) -> 0.091743575 | K29: =C29/AVERAGE(D29,D30) -> 0.0077761546 | L29: 0.027 | M29: 0.77 | N29: - | O29: 1.29
A30: Morgan Stanley | B30: 2022 | C30: 11179 | D30: 1180231 | E30: 101231 | F30: - | G30: 356646 | H30: 9327 | I30: 0.153 | J30: =C30/AVERAGE(E30,E31) -> 0.10757883 | K30: =C30/AVERAGE(D30,D31) -> 0.0094402439 | L30: 0.026 | M30: 0.73 | N30: - | O30: 1.32
A31: Morgan Stanley | B31: 2021 | C31: 15120 | D31: 1188140 | E31: 106598 | F31: 200761 | G31: 647574 | H31: 8045 | I31: 0.16 | J31: =C31/AVERAGE(E31,1115862) -> 0.024737006 | K31: =C31/AVERAGE(D31,103149) -> 0.02341846 | L31: 0.024 | M31: 0.67 | N31: =F31/G31 -> 0.31002017 | O31: 1.34
A32: U.S. Bancorp | B32: 2025 | C32: 7596 | D32: 692345 | E32: 65651 | F32: 391335 | G32: 522216 | H32: 16649 | I32: 0.108 | J32: =C32/AVERAGE(E32,E33) -> 0.12183718 | K32: =C32/AVERAGE(D32,D33) -> 0.011083687 | L32: 0.0272 | M32: 0.586 | N32: =F32/G32 -> 0.74937382 | O32: 1.065
A33: U.S. Bancorp | B33: 2024 | C33: 6329 | D33: 678318 | E33: 59040 | F33: 379832 | G33: 218309 | H33: 16289 | I33: 0.016 | J33: =C33/AVERAGE(E33,E34) -> 0.11009254 | K33: =C33/AVERAGE(D33,D34) -> 0.0094335334 | L33: 0.027 | M33: 0.623 | N33: =F33/G33 -> 1.7398825 | O33: 1.066
A34: U.S. Bancorp | B34: 2023 | C34: 5458 | D34: 663491 | E34: 55936 | F34: 373835 | G34: 512312 | H34: 17396 | I34: 0.099 | J34: =C34/AVERAGE(E34,E35) -> 0.10219251 | K34: =C34/AVERAGE(D34,D35) -> 0.0086935746 | L34: 0.029 | M34: 0.667 | N34: =F34/G34 -> 0.72970182 | O34: 1.09
A35: U.S. Bancorp | B35: 2022 | C35: 5795 | D35: 592149 | E35: 50882 | F35: 387318 | G35: 511697 | H35: 14846 | I35: 0.093 | J35: =C35/AVERAGE(E35,E36) -> 0.1100414 | K35: =C35/AVERAGE(D35,D36) -> 0.01339214 | L35: 0.0272 | M35: 0.614 | N35: =F35/G35 -> 0.75692842 | O35: 1.11
A36: U.S. Bancorp | B36: 2021 | C36: 7963 | D36: 273284 | E36: 54442 | F36: 312028 | G36: 475399 | H36: 12600 | I36: 0.1 | J36: =C36/AVERAGE(E36,53095) -> 0.14809786 | K36: =C36/AVERAGE(D36,553905) -> 0.019253157 | L36: 0.0249 | M36: 0.604 | N36: =F36/G36 -> 0.65634972 | O36: 1.15
A37: PNC Financial Services Group | B37: 2025 | C37: 6997 | D37: 573572 | E37: 60585 | F37: 331481 | G37: 440866 | H37: 14410 | I37: 0.106 | J37: =C37/AVERAGE(E37,E38) -> 0.12167638 | K37: =C37/AVERAGE(D37,D38) -> 0.012344634 | L37: 0.0283 | M37: 0.6 | N37: =F37/G37 -> 0.75188606 | O37: 1.07
A38: PNC Financial Services Group | B38: 2024 | C38: 5953 | D38: 560038 | E38: 54425 | F38: 316467 | G38: 426738 | H38: 13499 | I38: 0.105 | J38: =C38/AVERAGE(E38,E39) -> 0.11278252 | K38: =C38/AVERAGE(D38,D39) -> 0.010615022 | L38: 0.0266 | M38: 0.63 | N38: =F38/G38 -> 0.74159555 | O38: 1.07
A39: PNC Financial Services Group | B39: 2023 | C39: 5647 | D39: 561580 | E39: 51141 | F39: 321508 | G39: 421418 | H39: 13916 | I39: 0.099 | J39: =C39/AVERAGE(E39,E40) -> 0.11648943 | K39: =C39/AVERAGE(D39,D40) -> 0.010090605 | L39: 0.0276 | M39: 0.65 | N39: =F39/G39 -> 0.76291948 | O39: 1.07
A40: PNC Financial Services Group | B40: 2022 | C40: 6097 | D40: 557679 | E40: 45812 | F40: 326025 | G40: 436282 | H40: 13014 | I40: 0.091 | J40: =C40/AVERAGE(E40,E41) -> 0.12009297 | K40: =C40/AVERAGE(D40,D41) -> 0.010936588 | L40: 0.0265 | M40: 0.62 | N40: =F40/G40 -> 0.74728043 | O40: 1.08
A41: PNC Financial Services Group | B41: 2021 | C41: 6010 | D41: 557294 | E41: 55726 | F41: 288372 | G41: 457278 | H41: 10647 | I41: 0.103 | J41: =C41/AVERAGE(E41,54041) -> 0.10950468 | K41: =C41/AVERAGE(D41,466679) -> 0.011738591 | L41: 0.0229 | M41: 0.68 | N41: =F41/G41 -> 0.63062732 | O41: 1.1
A42: Truist Financial | B42: 2025 | C42: 5314 | D42: 547538 | E42: 65189 | F42: 330478 | G42: 400398 | H42: 14420 | I42: 0.108 | J42: =C42/AVERAGE(E42,E43) -> 0.082471987 | K42: =C42/AVERAGE(D42,D43) -> 0.0098524725 | L42: 0.0273 | M42: 0.645 | N42: =F42/G42 -> 0.82537375 | O42: 1.1
A43: Truist Financial | B43: 2024 | C43: 4820 | D43: 531176 | E43: 63679 | F43: 307771 | G43: 390524 | H43: 14091 | I43: 0.115 | J43: =C43/AVERAGE(E43,E44) -> 0.078417336 | K43: =C43/AVERAGE(D43,D44) -> 0.0090387005 | L43: 0.0275 | M43: 0.62 | N43: =F43/G43 -> 0.78809753 | O43: 1.11
A44: Truist Financial | B44: 2023 | C44: 1091 | D44: 535349 | E44: 59253 | F44: 313341 | G44: 395865 | H44: 14600 | I44: 0.101 | J44: =C44/AVERAGE(E44,E45) -> 0.01821521 | K44: =C44/AVERAGE(D44,D45) -> 0.0020007262 | L44: 0.0278 | M44: 0.918 | N44: =F44/G44 -> 0.79153499 | O44: 1.11
A45: Truist Financial | B45: 2022 | C45: 6263 | D45: 555255 | E45: 60537 | F45: 327435 | G45: 413495 | H45: 14316 | I45: 0.09 | J45: =C45/AVERAGE(E45,E46) -> 0.096496364 | K45: =C45/AVERAGE(D45,D46) -> 0.011423662 | L45: 0.0273 | M45: 0.633 | N45: =F45/G45 -> 0.79187173 | O45: 1.12
A46: Truist Financial | B46: 2021 | C46: 6033 | D46: 541241 | E46: 69271 | F46: 289513 | G46: 416488 | H46: 13006 | I46: 0.096 | J46: =C46/AVERAGE(E46,70912) -> 0.086073204 | K46: =C46/AVERAGE(D46,509227) -> 0.011486309 | L46: 0.0272 | M46: 0.61 | N46: =F46/G46 -> 0.69512927 | O46: 1.14
A47: Capital One | B47: 2025 | C47: 2453 | D47: 669009 | E47: 113616 | F47: 453622 | G47: 475771 | H47: 42878 | I47: 0.143 | J47: =C47/AVERAGE(E47,E48) -> 0.028130734 | K47: =C47/AVERAGE(D47,D48) -> 0.0042324007 | L47: 0.0784 | M47: 0.5708 | N47: =F47/G47 -> 0.95344609 | O47: 1.73
A48: Capital One | B48: 2024 | C48: 4750 | D48: 490144 | E48: 60784 | F48: 327775 | G48: 362707 | H48: 31208 | I48: 0.135 | J48: =C48/AVERAGE(E48,E49) -> 0.079917223 | K48: =C48/AVERAGE(D48,D49) -> 0.0098078893 | L48: 0.0688 | M48: 0.5493 | N48: =F48/G48 -> 0.90369086 | O48: 1.55
A49: Capital One | B49: 2023 | C49: 4887 | D49: 478464 | E49: 58089 | F49: 320472 | G49: 348413 | H49: 29241 | I49: 0.129 | J49: =C49/AVERAGE(E49,E50) -> 0.086332079 | K49: =C49/AVERAGE(D49,D50) -> 0.010467885 | L49: 0.0663 | M49: 0.5523 | N49: =F49/G49 -> 0.91980494 | O49: 1.67
A50: Capital One | B50: 2022 | C50: 7360 | D50: 455249 | E50: 55125 | F50: 312331 | G50: 332992 | H50: 27241 | I50: 0.125 | J50: =C50/AVERAGE(E50,E51) -> 0.12672831 | K50: =C50/AVERAGE(D50,D51) -> 0.016583486 | L50: 0.0667 | M50: 0.5595 | N50: =F50/G50 -> 0.93795346 | O50: 1.52
A51: Capital One | B51: 2021 | C51: 12390 | D51: 432381 | E51: 61029 | F51: 277340 | G51: 310980 | H51: 24171 | I51: 0.131 | J51: =C51/AVERAGE(E51,60204) -> 0.20439979 | K51: =C51/AVERAGE(D51,421602) -> 0.029016971 | L51: 0.0621 | M51: 0.5444 | N51: =F51/G51 -> 0.89182584 | O51: 1.49
A52: HSBC | B52: 2025 | C52: 23131 | D52: 3233034 | E52: 205525 | F52: 988399 | G52: 1786828 | H52: 34794 | I52: 0.149 | J52: =C52/AVERAGE(E52,E53) -> 0.11629521 | K52: =C52/AVERAGE(D52,D53) -> 0.0074018229 | L52: 0.0159 | M52: 0.534 | N52: =F52/G52 -> 0.55315845 | O52: 1.37
A53: HSBC | B53: 2024 | C53: 24999 | D53: 3017048 | E53: 192273 | F53: 930658 | G53: 1654955 | H53: 32733 | I53: 0.149 | J53: =C53/AVERAGE(E53,E54) -> 0.12990441 | K53: =C53/AVERAGE(D53,D54) -> 0.0082563194 | L53: 0.0156 | M53: 0.502 | N53: =F53/G53 -> 0.56234641 | O53: 1.38
A54: HSBC | B54: 2023 | C54: 24559 | D54: 3038677 | E54: 192610 | F54: 938535 | G54: 1611647 | H54: 35796 | I54: 0.148 | J54: =C54/AVERAGE(E54,E55) -> 0.13000818 | K54: =C54/AVERAGE(D54,D55) -> 0.0082027758 | L54: 0.0166 | M54: 0.485 | N54: =F54/G54 -> 0.58234527 | O54: 1.36
A55: HSBC | B55: 2022 | C55: 16249 | D55: 2949296 | E55: 185197 | F55: 923561 | G55: 1570303 | H55: 30377 | I55: 0.142 | J55: =C55/AVERAGE(E55,E56) -> 0.08290856 | K55: =C55/AVERAGE(D55,D56) -> 0.0055013894 | L55: 0.0148 | M55: 0.644 | N55: =F55/G55 -> 0.58814191 | O55: 1.32
A56: HSBC | B56: 2021 | C56: 14693 | D56: 2957939 | E56: 206777 | F56: 1045814 | G56: 1710574 | H56: 26489 | I56: 0.158 | J56: =C56/AVERAGE(E56,200589) -> 0.072136604 | K56: =C56/AVERAGE(D56,2958548) -> 0.0049667987 | L56: 0.012 | M56: 0.699 | N56: =F56/G56 -> 0.61138191 | O56: 1.39
A57: Barklays PLC | B57: 2025 | C57: 6175 | D57: 1544165 | E57: 78236 | F57: 355892 | G57: 565200 | H57: 36188 | I57: 0.136 | J57: =C57/AVERAGE(E57,E58) -> 0.081941652 | K57: =C57/AVERAGE(D57,D58) -> 0.0040328282 | L57: 0.046 | M57: 0.61 | N57: =F57/G57 -> 0.62967445 | O57: 1.7
A58: Barklays PLC | B58: 2024 | C58: 5316 | D58: 1518202 | E58: 72481 | F58: 337846 | G58: 547460 | H58: 38326 | I58: 0.136 | J58: =C58/AVERAGE(E58,E59) -> 0.073656864 | K58: =C58/AVERAGE(D58,D59) -> 0.0035491001 | L58: 0.0428 | M58: 0.62 | N58: =F58/G58 -> 0.61711541 | O58: 1.724
A59: Barklays PLC | B59: 2023 | C59: 4274 | D59: 1477487 | E59: 71864 | F59: 333288 | G59: 526462 | H59: 12709 | I59: 0.138 | J59: =C59/AVERAGE(E59,E60) -> 0.060570845 | K59: =C59/AVERAGE(D59,D60) -> 0.0028928505 | L59: 0.042 | M59: 0.67 | N59: =F59/G59 -> 0.63307133 | O59: 1.61
A60: Barklays PLC | B60: 2022 | C60: 5023 | D60: 1477384 | E60: 69260 | F60: 244834 | G60: 527949 | H60: 10047 | I60: 0.139 | J60: =C60/AVERAGE(E60,E61) -> 0.073790601 | K60: =C60/AVERAGE(D60,D61) -> 0.0035536859 | L60: 0.0355 | M60: 0.67 | N60: =F60/G60 -> 0.46374555 | O60: 1.51
A61: Barklays PLC | B61: 2021 | C61: 6385 | D61: 1349540 | E61: 66882 | F61: 305081 | G61: 463692 | H61: 10121 | I61: 0.138 | J61: =C61/AVERAGE(E61,67735) -> 0.094861719 | K61: =C61/AVERAGE(D61,1385496) -> 0.0046690427 | L61: 0.0252 | M61: 0.63 | N61: =F61/G61 -> 0.65793889 | O61: 1.51
A62: Lloyds BG | B62: 2025 | C62: 18301 | D62: 944072 | E62: 47867 | F62: 481463 | G62: 496457 | H62: 13635 | I62: 0.14 | J62: =C62/AVERAGE(E62,E63) -> 0.39040051 | K62: =C62/AVERAGE(D62,D63) -> 0.019776644 | L62: 0.0306 | M62: 0.586 | N62: =F62/G62 -> 0.96979799 | O62: 1.45
A63: Lloyds BG | B63: 2024 | C63: 17117 | D63: 906697 | E63: 45888 | F63: 459857 | G63: 482745 | H63: 12845 | I63: 0.142 | J63: =C63/AVERAGE(E63,E64) -> 0.36710883 | K63: =C63/AVERAGE(D63,D64) -> 0.019144926 | L63: 0.0295 | M63: 0.604 | N63: =F63/G63 -> 0.95258781 | O63: 1.46
A64: Lloyds BG | B64: 2023 | C64: 17932 | D64: 881453 | E64: 47365 | F64: 449745 | G64: 471396 | H64: 13765 | I64: 0.146 | J64: =C64/AVERAGE(E64,E65) -> 0.39291818 | K64: =C64/AVERAGE(D64,D65) -> 0.020437109 | L64: 0.0311 | M64: 0.547 | N64: =F64/G64 -> 0.95407046 | O64: 1.42
A65: Lloyds BG | B65: 2022 | C65: 17465 | D65: 873394 | E65: 43911 | F65: 454899 | G65: 475331 | H65: 13172 | I65: 0.151 | J65: =C65/AVERAGE(E65,E66) -> 0.35986936 | K65: =C65/AVERAGE(D65,D66) -> 0.019847504 | L65: 0.0294 | M65: 0.504 | N65: =F65/G65 -> 0.95701522 | O65: 1.44
A66: Lloyds BG | B66: 2021 | C66: 15763 | D66: 886525 | E66: 53152 | F66: 448567 | G66: 476344 | H66: 11163 | I66: 0.173 | J66: =C66/AVERAGE(E66,49413) -> 0.30737581 | K66: =C66/AVERAGE(D66,871269) -> 0.01793498 | L66: 0.0254 | M66: 0.61 | N66: =F66/G66 -> 0.9416871 | O66: 1.35
A67: BNP Paribas | B67: 2025 | C67: 12225 | D67: 2792981 | E67: 125513 | F67: 897358 | G67: 1075564 | H67: 21203 | I67: 0.126 | J67: =C67/AVERAGE(E67,E68) -> 0.096163301 | K67: =C67/AVERAGE(D67,D68) -> 0.0044471614 | L67: 0.0077 | M67: 0.612 | N67: =F67/G67 -> 0.8343139 | O67: 1.34
A68: BNP Paribas | B68: 2024 | C68: 11688 | D68: 2704908 | E68: 128742 | F68: 900141 | G68: 1034857 | H68: 19524 | I68: 0.129 | J68: =C68/AVERAGE(E68,E69) -> 0.091496923 | K68: =C68/AVERAGE(D68,D69) -> 0.0044135581 | L68: 0.0074 | M68: 0.618 | N68: =F68/G68 -> 0.86982163 | O68: 1.37
A69: BNP Paribas | B69: 2023 | C69: 10975 | D69: 2591499 | E69: 126742 | F69: 859200 | G69: 988549 | H69: 19058 | I69: 0.132 | J69: =C69/AVERAGE(E69,E70) -> 0.088335667 | K69: =C69/AVERAGE(D69,D70) -> 0.0041746903 | L69: 0.0072 | M69: 0.63 | N69: =F69/G69 -> 0.86915267 | O69: 1.48
A70: BNP Paribas | B70: 2022 | C70: 10196 | D70: 2666376 | E70: 121742 | F70: 857020 | G70: 1008054 | H70: 23168 | I70: 0.123 | J70: =C70/AVERAGE(E70,E71) -> 0.085098569 | K70: =C70/AVERAGE(D70,D71) -> 0.003846952 | L70: 0.0087 | M70: 0.668 | N70: =F70/G70 -> 0.85017271 | O70: 1.32
A71: BNP Paribas | B71: 2021 | C71: 9488 | D71: 2634444 | E71: 117886 | F71: 814000 | G71: 957684 | H71: 21209 | I71: 0.129 | J71: =C71/AVERAGE(E7,1117349) -> 0.013357811 | K71: =C71/AVERAGE(D71,2488491) -> 0.0037041266 | L71: 0.0083 | M71: 0.673 | N71: =F71/G71 -> 0.84996721 | O71: 1.43
A72: Credit Agricole S.A. | B72: 2025 | C72: 7074 | D72: 2374307 | E72: 85864 | F72: 559235 | G72: 894540 | H72: 15308 | I72: 0.118 | J72: =C72/AVERAGE(E72,E73) -> 0.083629378 | K72: =C72/AVERAGE(D72,D73) -> 0.0030204379 | L72: 0.0065 | M72: 0.557 | N72: =F72/G72 -> 0.62516489 | O72: 1.41
A73: Credit Agricole S.A. | B73: 2024 | C73: 7087 | D73: 2309782 | E73: 83311 | F73: 548101 | G73: 868115 | H73: 14299 | I73: 0.117 | J73: =C73/AVERAGE(E73,E74) -> 0.086834528 | K73: =C73/AVERAGE(D73,D74) -> 0.0031503518 | L73: 0.0063 | M73: 0.544 | N73: =F73/G73 -> 0.63136912 | O73: 1.45
A74: Credit Agricole S.A. | B74: 2023 | C74: 8258 | D74: 2189398 | E74: 79919 | F74: 516281 | G74: 834998 | H74: 14244 | I74: 0.118 | J74: =C74/AVERAGE(E74,E75) -> 0.10766693 | K74: =C74/AVERAGE(D74,D75) -> 0.0037906651 | L74: 0.0063 | M74: 0.554 | N74: =F74/G74 -> 0.61830208 | O74: 1.43
A75: Credit Agricole S.A. | B75: 2022 | C75: 5437 | D75: 2167621 | E75: 73480 | F75: 489757 | G75: 827977 | H75: 12864 | I75: 0.112 | J75: =C75/AVERAGE(E75,E76) -> 0.072302455 | K75: =C75/AVERAGE(D75,D76) -> 0.0025636697 | L75: 0.0059 | M75: 0.582 | N75: =F75/G75 -> 0.59151039 | O75: 1.48
A76: Credit Agricole S.A. | B76: 2021 | C76: 5844 | D76: 2073955 | E76: 76916 | F76: 459905 | G76: 781177 | H76: 12121 | I76: 0.119 | J76: =C76/AVERAGE(E76,126474) -> 0.057465952 | K76: =C76/AVERAGE(D76,1961100) -> 0.0028966148 | L76: 0.0059 | M76: 0.578 | N76: =F76/G76 -> 0.58873341 | O76: 1.53
A77: Deutsche Bank | B77: 2025 | C77: 6064 | D77: 1425000 | E77: 80203 | F77: 479000 | G77: 692000 | H77: 15891 | I77: 0.142 | J77: =C77/AVERAGE(E77,E78) -> 0.081285229 | K77: =C77/AVERAGE(D77,D78) -> 0.0043129445 | L77: 0.011 | M77: 0.644 | N77: =F77/G77 -> 0.69219653 | O77: 1.44
A78: Deutsche Bank | B78: 2024 | C78: 2698 | D78: 1387000 | E78: 69000 | F78: 479000 | G78: 666000 | H78: 13065 | I78: 0.138 | J78: =C78/AVERAGE(E78,E79) -> 0.040571429 | K78: =C78/AVERAGE(D78,D79) -> 0.001999259 | L78: 0.0093 | M78: 0.763 | N78: =F78/G78 -> 0.71921922 | O78: 1.41
A79: Deutsche Bank | B79: 2023 | C79: 4210 | D79: 1312000 | E79: 64000 | F79: 477000 | G79: 646000 | H79: 13602 | I79: 0.137 | J79: =C79/AVERAGE(E79,E80) -> 0.068455285 | K79: =C79/AVERAGE(D79,D80) -> 0.0032039574 | L79: 0.0101 | M79: 0.75 | N79: =F79/G79 -> 0.73839009 | O79: 1.4
A80: Deutsche Bank | B80: 2022 | C80: 5025 | D80: 1316000 | E80: 59000 | F80: 482000 | G80: 600000 | H80: 10000 | I80: 0.134 | J80: =C80/AVERAGE(E80,E81) -> 0.085877618 | K80: =C80/AVERAGE(D80,D81) -> 0.0038068283 | L80: 0.008 | M80: 0.75 | N80: =F80/G80 -> 0.80333333 | O80: 1.4
A81: Deutsche Bank | B81: 2021 | C81: 1940 | D81: 1323993 | E81: 58027 | F81: 471319 | G81: 603750 | H81: 8000 | I81: 0.132 | J81: =C81/AVERAGE(E81,62196) -> 0.032273359 | K81: =C81/AVERAGE(D81,1325259) -> 0.0014645643 | L81: 0.0065 | M81: 0.846 | N81: =F81/G81 -> 0.78065259 | O81: 1.4
A82: Commerzbank | B82: 2025 | C82: 2625 | D82: 551977 | E82: 30000 | F82: 273966 | G82: 390279 | H82: 8226 | I82: 0.149 | J82: =C82/AVERAGE(E82,E83) -> 0.0875 | K82: =C82/AVERAGE(D82,D83) -> 0.0047209513 | L82: - | M82: 0.57 | N82: =F82/G82 -> 0.70197474 | O82: 1.453
A83: Commerzbank | B83: 2024 | C83: 2677 | D83: 560087 | E83: 30000 | F83: 278400 | G83: 395204 | H83: 8331 | I83: 0.148 | J83: =C83/AVERAGE(E83,E84) -> 0.090745763 | K83: =C83/AVERAGE(D83,D84) -> 0.0047223607 | L83: - | M83: 0.588 | N83: =F83/G83 -> 0.70444631 | O83: 1.46
A84: Commerzbank | B84: 2023 | C84: 2224 | D84: 573668 | E84: 29000 | F84: 286001 | G84: 391643 | H84: 8368 | I84: 0.151 | J84: =C84/AVERAGE(E84,E85) -> 0.079428571 | K84: =C84/AVERAGE(D84,D85) -> 0.0038494625 | L84: - | M84: 0.561 | N84: =F84/G84 -> 0.73025945 | O84: 1.43
A85: Commerzbank | B85: 2022 | C85: 1435 | D85: 581818 | E85: 27000 | F85: 292509 | G85: 396540 | H85: 6459 | I85: 0.146 | J85: =C85/AVERAGE(E85,E86) -> 0.050504162 | K85: =C85/AVERAGE(D85,D86) -> 0.002720735 | L85: - | M85: 0.554 | N85: =F85/G85 -> 0.7376532 | O85: 1.51
A86: Commerzbank | B86: 2021 | C86: 430 | D86: 473044 | E86: 29827 | F86: 282000 | G86: 443000 | H86: 4849 | I86: 0.136 | J86: =C86/AVERAGE(E86,29827) -> 0.014416468 | K86: =C86/AVERAGE(D86,506613) -> 0.00087785827 | L86: - | M86: 0.793 | N86: =F86/G86 -> 0.63656885 | O86: 1.5
A87: Santander Group | B87: 2025 | C87: 14101 | D87: 1867515 | E87: 112748 | F87: 1037288 | G87: 1041200 | H87: 42348 | I87: 0.135 | J87: =C87/AVERAGE(E87,E88) -> 0.12814722 | K87: =C87/AVERAGE(D87,D88) -> 0.0076127059 | L87: 0.0229 | M87: 0.412 | N87: =F87/G87 -> 0.9962428 | O87: 1.55
A88: Santander Group | B88: 2024 | C88: 12574 | D88: 1837081 | E88: 107327 | F88: 1054069 | G88: 1055936 | H88: 46668 | I88: 0.128 | J88: =C88/AVERAGE(E88,E89) -> 0.11886486 | K88: =C88/AVERAGE(D88,D89) -> 0.0069199258 | L88: 0.0257 | M88: 0.418 | N88: =F88/G88 -> 0.9982319 | O88: 1.68
A89: Santander Group | B89: 2023 | C89: 11076 | D89: 1797062 | E89: 104241 | F89: 1036349 | G89: 1047169 | H89: 43261 | I89: 0.123 | J89: =C89/AVERAGE(E89,E90) -> 0.10975791 | K89: =C89/AVERAGE(D89,D90) -> 0.0062722961 | L89: 0.0245 | M89: 0.441 | N89: =F89/G89 -> 0.98966738 | O89: 1.66
A90: Santander Group | B90: 2022 | C90: 9605 | D90: 1734659 | E90: 97585 | F90: 1036004 | G90: 1025401 | H90: 38619 | I90: 0.1204 | J90: =C90/AVERAGE(E90,E91) -> 0.098696041 | K90: =C90/AVERAGE(D90,D91) -> 0.0057679131 | L90: 0.0232 | M90: 0.458 | N90: =F90/G90 -> 1.0103403 | O90: 1.52
A91: Santander Group | B91: 2021 | C91: 8124 | D91: 1595835 | E91: 97053 | F91: 972682 | G91: 918344 | H91: 33370 | I91: 0.1251 | J91: =C91/AVERAGE(E91,91980) -> 0.085953246 | K91: =C91/AVERAGE(D91,1508250) -> 0.0052343927 | L91: 0.0215 | M91: 0.462 | N91: =F91/G91 -> 1.0591695 | O91: 1.63
A92: BBVA Group | B92: 2025 | C92: 10511 | D92: 859576 | E92: 61798 | F92: 460401 | G92: 502501 | H92: 26280 | I92: 0.127 | J92: =C92/AVERAGE(E92,E93) -> 0.17257741 | K92: =C92/AVERAGE(D92,D93) -> 0.012881301 | L92: 0.0322 | M92: 0.388 | N92: =F92/G92 -> 0.91621907 | O92: 1.43
A93: BBVA Group | B93: 2024 | C93: 10054 | D93: 772402 | E93: 60014 | F93: 412477 | G93: 447646 | H93: 25267 | I93: 0.1288 | J93: =C93/AVERAGE(E93,E94) -> 0.17442899 | K93: =C93/AVERAGE(D93,D94) -> 0.01299 | L93: 0.031 | M93: 0.4 | N93: =F93/G93 -> 0.92143569 | O93: 1.34
A94: BBVA Group | B94: 2023 | C94: 8019 | D94: 775558 | E94: 55265 | F94: 388912 | G94: 413487 | H94: 23089 | I94: 0.1267 | J94: =C94/AVERAGE(E94,E95) -> 0.1516137 | K94: =C94/AVERAGE(D94,D95) -> 0.010780762 | L94: 0.0298 | M94: 0.417 | N94: =F94/G94 -> 0.94056645 | O94: 1.49
A95: BBVA Group | B95: 2022 | C95: 6420 | D95: 712092 | E95: 50517 | F95: 368588 | G95: 394404 | H95: 19124 | I95: 0.1261 | J95: =C95/AVERAGE(E95,E96) -> 0.12933509 | K95: =C95/AVERAGE(D95,D96) -> 0.009338338 | L95: 0.0273 | M95: 0.432 | N95: =F95/G95 -> 0.93454427 | O95: 1.59
A96: BBVA Group | B96: 2021 | C96: 4653 | D96: 662885 | E96: 48760 | F96: 330055 | G96: 349761 | H96: 14686 | I96: 0.1261 | J96: =C96/AVERAGE(E96,50020) -> 0.094209354 | K96: =C96/AVERAGE(D96,733797) -> 0.006662934 | L96: 0.0214 | M96: 0.452 | N96: =F96/G96 -> 0.94365867 | O96: 1.65
A97: Unicredit | B97: 2025 | C97: 10915 | D97: 870238 | E97: 67771 | F97: 433541 | G97: 535371 | H97: 13735 | I97: 0.1475 | J97: =C97/AVERAGE(E97,E98) -> 0.16764968 | K97: =C97/AVERAGE(D97,D98) -> 0.013196376 | L97: 0.0166 | M97: 0.385 | N97: =F97/G97 -> 0.80979545 | O97: 1.43
A98: Unicredit | B98: 2024 | C98: 9719 | D98: 784004 | E98: 62441 | F98: 418378 | G98: 500970 | H98: 14671 | I98: 0.1596 | J98: =C98/AVERAGE(E98,E99) -> 0.15363579 | K98: =C98/AVERAGE(D98,D99) -> 0.012388956 | L98: 0.0177 | M98: 0.379 | N98: =F98/G98 -> 0.83513584 | O98: 1.44
A99: Unicredit | B99: 2023 | C99: 9507 | D99: 784974 | E99: 64079 | F99: 429452 | G99: 497394 | H99: 14348 | I99: 0.1614 | J99: =C99/AVERAGE(E99,E100) -> 0.14922538 | K99: =C99/AVERAGE(D99,D100) -> 0.011574515 | L99: 0.0183 | M99: 0.397 | N99: =F99/G99 -> 0.86340406 | O99: 1.54
A100: Unicredit | B100: 2022 | C100: 6458 | D100: 857773 | E100: 63339 | F100: 455781 | G100: 594300 | H100: 10686 | I100: 0.16 | J100: =C100/AVERAGE(E100,E101) -> 0.10335529 | K100: =C100/AVERAGE(D100,D101) -> 0.0072788998 | L100: 0.0122 | M100: 0.47 | N100: =F100/G100 -> 0.76692075 | O100: 1.61
...

Sheet Ratio 
A1: Bank | B1: Avg ROE | C1: Avg ROA | D1: Avg Net Yield | E1: Avg CET1 | F1: Avg Cost-to-Income | G1: Avg LCR
A2: JPMorgan Chase | B2: =AVERAGE('Raw Data'!J2,'Raw Data'!J3,'Raw Data'!J4,'Raw Data'!J5,'Raw Data'!J7) -> 0.1451015 | C2: =AVERAGE('Raw Data'!K2:K6) -> 0.013048168 | D2: =AVERAGE('Raw Data'!L2:L6) -> 0.0234 | E2: =AVERAGE('Raw Data'!I2:I6) -> 0.1432 | F2: =AVERAGE('Raw Data'!M2:M6) -> 0.54 | G2: =AVERAGE('Raw Data'!O2:O6) -> 1.12
A3: Bank of America | B3: =AVERAGE('Raw Data'!J7:J11) -> 0.10146089 | C3: =AVERAGE('Raw Data'!K7:K11) -> 0.0090764022 | D3: =AVERAGE('Raw Data'!L7:L11) -> 0.01932 | E3: =AVERAGE('Raw Data'!I7:I11) -> 0.1138 | F3: =AVERAGE('Raw Data'!M7:M11) -> 0.64664 | G3: =AVERAGE('Raw Data'!O7:O11) -> 1.15
A4: Wells Fargo | B4: =AVERAGE('Raw Data'!J12:J16) -> 0.10282571 | C4: =AVERAGE('Raw Data'!K12:K16) -> 0.0097347863 | D4: =AVERAGE('Raw Data'!L12:L16) -> 0.0259 | E4: =AVERAGE('Raw Data'!I12:I16) -> 0.1101 | F4: =AVERAGE('Raw Data'!M12:M16) -> 0.69 | G4: =AVERAGE('Raw Data'!O12:O16) -> 1.218
A5: Citigroup | B5: =AVERAGE('Raw Data'!J17:J21) -> 0.071528167 | C5: =AVERAGE('Raw Data'!K17:K21) -> 0.0061617094 | D5: =AVERAGE('Raw Data'!L17:L21) -> 0.02314 | E5: =AVERAGE('Raw Data'!I17:I21) -> 0.13092 | F5: =AVERAGE('Raw Data'!M17:M21) -> 0.6752 | G5: =AVERAGE('Raw Data'!O17:O21) -> 1.16
A6: Goldman Sachs | B6: =AVERAGE('Raw Data'!J22:J26) -> 0.12814501 | C6: =AVERAGE('Raw Data'!K22:K26) -> 0.0096416541 | D6: =AVERAGE('Raw Data'!L22:L26) -> 0.023575 | E6: =AVERAGE('Raw Data'!I22:I26) -> 0.1472 | F6: =AVERAGE('Raw Data'!M22:M26) -> 0.6434 | G6: =AVERAGE('Raw Data'!O22:O26) -> 1.256
A7: Morgan Stanley | B7: =AVERAGE('Raw Data'!J27:J31) -> 0.10238431 | C7: =AVERAGE('Raw Data'!K27:K31) -> 0.012957707 | D7: =AVERAGE('Raw Data'!L27:L31) -> 0.0256 | E7: =AVERAGE('Raw Data'!I27:I31) -> 0.1554 | F7: =AVERAGE('Raw Data'!M27:M31) -> 0.712 | G7: =AVERAGE('Raw Data'!O27:O31) -> 1.318
A8: U.S. Bancorp | B8: =AVERAGE('Raw Data'!J32:J36) -> 0.1184523 | C8: =AVERAGE('Raw Data'!K32:K36) -> 0.012371219 | D8: =AVERAGE('Raw Data'!L32:L36) -> 0.02706 | E8: =AVERAGE('Raw Data'!J32:J36) -> 0.1184523 | F8: =AVERAGE('Raw Data'!M32:M36) -> 0.6188 | G8: =AVERAGE('Raw Data'!O32:O36) -> 1.0962
A9: PNC Financial Services Group | B9: =AVERAGE('Raw Data'!J37:J41) -> 0.1161092 | C9: =AVERAGE('Raw Data'!K37:K41) -> 0.011145088 | D9: =AVERAGE('Raw Data'!L37:L41) -> 0.02638 | E9: =AVERAGE('Raw Data'!I37:I41) -> 0.1008 | F9: =AVERAGE('Raw Data'!M37:M41) -> 0.636 | G9: =AVERAGE('Raw Data'!O37:O41) -> 1.078
A10: Truist Financial | B10: =AVERAGE('Raw Data'!J42:J46) -> 0.07233482 | C10: =AVERAGE('Raw Data'!K42:K46) -> 0.0087603741 | D10: =AVERAGE('Raw Data'!L42:L46) -> 0.02742 | E10: =AVERAGE('Raw Data'!I42:I46) -> 0.102 | F10: =AVERAGE('Raw Data'!M42:M46) -> 0.6852 | G10: =AVERAGE('Raw Data'!O42:O46) -> 1.116
A11: Capital One | B11: =AVERAGE('Raw Data'!J47:J51) -> 0.10510163 | C11: =AVERAGE('Raw Data'!K47:K51) -> 0.014021726 | D11: =AVERAGE('Raw Data'!L47:L51) -> 0.06846 | E11: =AVERAGE('Raw Data'!I47:I51) -> 0.1326 | F11: =AVERAGE('Raw Data'!M47:M51) -> 0.55526 | G11: =AVERAGE('Raw Data'!O47:O51) -> 1.592
A12: HSBC | B12: =AVERAGE('Raw Data'!J52:J56) -> 0.10625059 | C12: =AVERAGE('Raw Data'!K52:K56) -> 0.0068658212 | D12: =AVERAGE('Raw Data'!L52:L56) -> 0.01498 | E12: =AVERAGE('Raw Data'!I52:I56) -> 0.1492 | F12: =AVERAGE('Raw Data'!M52:M56) -> 0.5728 | G12: =AVERAGE('Raw Data'!O52:O56) -> 1.364
A13: Barclays PLC | B13: =AVERAGE('Raw Data'!J57:J61) -> 0.076964336 | C13: =AVERAGE('Raw Data'!K57:K61) -> 0.0037395015 | D13: =AVERAGE('Raw Data'!L57:L61) -> 0.0383 | E13: =AVERAGE('Raw Data'!I57:I61) -> 0.1374 | F13: =AVERAGE('Raw Data'!M57:M61) -> 0.64 | G13: =AVERAGE('Raw Data'!O57:O61) -> 1.6108
A14: Lloyds BG | B14: =AVERAGE('Raw Data'!J62:J66) -> 0.36353454 | C14: =AVERAGE('Raw Data'!K62:K66) -> 0.019428233 | D14: =SUM(AVERAGE('Raw Data'!L62:L66)) -> 0.0292 | E14: =AVERAGE('Raw Data'!I62:I66) -> 0.1504 | F14: =AVERAGE('Raw Data'!M62:M66) -> 0.5702 | G14: =AVERAGE('Raw Data'!O62:O66) -> 1.424
A15: BNP Paribas | B15: =AVERAGE('Raw Data'!J67:J71) -> 0.074890454 | C15: =AVERAGE('Raw Data'!K67:K71) -> 0.0041172977 | D15: =AVERAGE('Raw Data'!L67:L71) -> 0.00786 | E15: =AVERAGE('Raw Data'!I67:I71) -> 0.1278 | F15: =AVERAGE('Raw Data'!M67:M71) -> 0.6402 | G15: =AVERAGE('Raw Data'!O67:O71) -> 1.388
A16: Credit Agricole S.A. | B16: =AVERAGE('Raw Data'!J72:J76) -> 0.081579849 | C16: =AVERAGE('Raw Data'!K72:K76) -> 0.0030843479 | D16: =AVERAGE('Raw Data'!L72:L76) -> 0.00618 | E16: =AVERAGE('Raw Data'!I72:I76) -> 0.1168 | F16: =AVERAGE('Raw Data'!M72:M76) -> 0.563 | G16: =AVERAGE('Raw Data'!O72:O76) -> 1.46
A17: Deutsche Bank | B17: =AVERAGE('Raw Data'!J77:J81) -> 0.061692584 | C17: =AVERAGE('Raw Data'!K77:K81) -> 0.0029575107 | D17: =AVERAGE('Raw Data'!L77:L81) -> 0.00898 | E17: =AVERAGE('Raw Data'!I77:I81) -> 0.1366 | F17: =AVERAGE('Raw Data'!M77:M81) -> 0.7506 | G17: =AVERAGE('Raw Data'!O77:O81) -> 1.41
A18: Commerzbank | B18: =AVERAGE('Raw Data'!J82:J86) -> 0.064518993 | C18: =AVERAGE('Raw Data'!K82:K86) -> 0.0033782735 | D18: - | E18: =AVERAGE('Raw Data'!I82:I86) -> 0.146 | F18: =AVERAGE('Raw Data'!M82:M86) -> 0.6132 | G18: =AVERAGE('Raw Data'!O82:O86) -> 1.4706
A19: Santander Group | B19: =AVERAGE('Raw Data'!J87:J91) -> 0.10828386 | C19: =AVERAGE('Raw Data'!K87:K91) -> 0.0063614468 | D19: =AVERAGE('Raw Data'!L87:L91) -> 0.02356 | E19: =AVERAGE('Raw Data'!I87:I91) -> 0.1263 | F19: =AVERAGE('Raw Data'!M87:M91) -> 0.4382 | G19: =AVERAGE('Raw Data'!O87:O91) -> 1.608
A20: BBVA Group | B20: =AVERAGE('Raw Data'!J92:J96) -> 0.14443291 | C20: =AVERAGE('Raw Data'!K92:K96) -> 0.010530667 | D20: =AVERAGE('Raw Data'!L92:L96) -> 0.02834 | E20: =AVERAGE('Raw Data'!I92:I96) -> 0.12694 | F20: =AVERAGE('Raw Data'!M92:M96) -> 0.4178 | G20: =AVERAGE('Raw Data'!O92:O96) -> 1.5
A21: UniCredit | B21: =AVERAGE('Raw Data'!J97:J101) -> 0.11985846 | C21: =AVERAGE('Raw Data'!K97:K101) -> 0.0092210599 | D21: =AVERAGE('Raw Data'!L97:L101) -> 0.01488 | E21: =AVERAGE('Raw Data'!I97:I101) -> 0.15576 | F21: =AVERAGE('Raw Data'!M97:M101) -> 0.4354 | G21: =AVERAGE('Raw Data'!O97:O101) -> 1.568
A22: Intesa Sanpaolo | B22: =AVERAGE('Raw Data'!J102:J106) -> 0.10483435 | C22: =AVERAGE('Raw Data'!K102:K106) -> 0.0064837999 | D22: - | E22: =AVERAGE('Raw Data'!I102:I106) -> 0.1364 | F22: =AVERAGE('Raw Data'!M102:M106) -> 0.479 | G22: =AVERAGE('Raw Data'!O102:O106) -> 1.752
A23: UBS Group | B23: =AVERAGE('Raw Data'!J107:J111) -> 0.15747334 | C23: =AVERAGE('Raw Data'!K107:K111) -> 0.0082480656 | D23: =AVERAGE('Raw Data'!L107:L111) -> 0.00516 | E23: =AVERAGE('Raw Data'!I107:I111) -> 0.1444 | F23: =AVERAGE('Raw Data'!M107:M111) -> 0.8132 | G23: =AVERAGE('Raw Data'!O107:O111) -> 1.8092
A24: Commonwealth Bank Australia | B24: =AVERAGE('Raw Data'!J112:J115) -> 0.1342248 | C24: =AVERAGE('Raw Data'!K112:K116) -> 0.0079882314 | D24: =AVERAGE('Raw Data'!L112:L116) -> 0.01742 | E24: =AVERAGE('Raw Data'!I112:I116) -> 0.1228 | F24: =AVERAGE('Raw Data'!M112:M116) -> 0.4542 | G24: =AVERAGE('Raw Data'!O112:O116) -> 1.312
A25: Mitsubishi UFJ Financial Group | B25: =AVERAGE('Raw Data'!J117:J121) -> 0.048286953 | C25: =AVERAGE('Raw Data'!K117:K121) -> 0.002213808 | D25: =AVERAGE('Raw Data'!L117:L121) -> 0.0044 | E25: =AVERAGE('Raw Data'!I117:I121) -> 0.1232 | F25: =AVERAGE('Raw Data'!M117:M121) -> 0.578 | G25: =AVERAGE('Raw Data'!O117:O121) -> 1.512
A26: Sumitomo Mitsui Financial Group | B26: =AVERAGE('Raw Data'!J122:J126) -> 0.050207476 | C26: =AVERAGE('Raw Data'!K122:K126) -> 0.0026815818 | D26: =AVERAGE('Raw Data'!L122:L126) -> 0.00672 | E26: =AVERAGE('Raw Data'!I122:I126) -> 0.13964 | F26: =AVERAGE('Raw Data'!M122:M126) -> 0.5572 | G26: =AVERAGE('Raw Data'!O122:O126) -> 1.362
A27: Industrial and Commercial Bank of China | B27: =AVERAGE('Raw Data'!J127:J131) -> 0.097897957 | C27: =AVERAGE('Raw Data'!K127:K131) -> 0.0085306517 | D27: =AVERAGE('Raw Data'!L127:L131) -> 0.0151 | E27: =AVERAGE('Raw Data'!I127:I131) -> 0.13748 | F27: =AVERAGE('Raw Data'!M127:M131) -> 0.28154 | G27: =AVERAGE('Raw Data'!O127:O131) -> 1.262
A28: China Construction Bank | B28: =AVERAGE('Raw Data'!J132:J135) -> 0.10554066 | C28: =AVERAGE('Raw Data'!K132:K136) -> 0.0090088645 | D28: =AVERAGE('Raw Data'!L132:L136) -> 0.016025 | E28: =AVERAGE('Raw Data'!I132:I136) -> 0.13908 | F28: =AVERAGE('Raw Data'!M132:M136) -> 0.28602 | G28: =AVERAGE('Raw Data'!O132:O136) -> 1.264
A29: DBS Group Holdings | B29: =AVERAGE('Raw Data'!J137:J141) -> 0.1508935 | C29: =AVERAGE('Raw Data'!K137:K141) -> 0.012299834 | D29: =AVERAGE('Raw Data'!L137:L141) -> 0.01444 | E29: =AVERAGE('Raw Data'!I137:I141) -> 0.1552 | F29: =AVERAGE('Raw Data'!M138:M142) -> 0.4222 | G29: =AVERAGE('Raw Data'!O137:O141) -> 1.442
A30: United Overseas Bank | B30: =AVERAGE('Raw Data'!J142:J146) -> 0.11292589 | C30: =AVERAGE('Raw Data'!K142:K146) -> 0.010185407 | D30: =AVERAGE('Raw Data'!L142:L146) -> 0.01676 | E30: =AVERAGE('Raw Data'!I142:I146) -> 0.1416 | F30: =AVERAGE('Raw Data'!M142:M146) -> 0.446 | G30: =AVERAGE('Raw Data'!O142:O146) -> 1.42
A31: Maybank | B31: =AVERAGE('Raw Data'!J147:J151) -> 0.10264507 | C31: =SUM(AVERAGE('Raw Data'!K147:K151)) -> 0.0094272943 | D31: =AVERAGE('Raw Data'!L147:L151) -> 0.0676 | E31: =AVERAGE('Raw Data'!I147:I151) -> 0.15952 | F31: =AVERAGE('Raw Data'!M147:M151) -> 0.4742 | G31: =AVERAGE('Raw Data'!O147:O151) -> 1.3733333

Sheet Dashboard
A1: Bank Financial Analysis Dashboard
A3: Top 5 Banks
A4: 1. Lloyds BG
A5: 2.BBVA Group
A6: 3.DBS Group Holdings
A7: 4.Capital One
A8: 5.UniCredit
